README.md
setup.py
keras_tuner_cv/__init__.py
keras_tuner_cv/inner_cv.py
keras_tuner_cv/outer_cv.py
keras_tuner_cv/utils.py
keras_tuner_cv.egg-info/PKG-INFO
keras_tuner_cv.egg-info/SOURCES.txt
keras_tuner_cv.egg-info/dependency_links.txt
keras_tuner_cv.egg-info/requires.txt
keras_tuner_cv.egg-info/top_level.txt